wclr/__init__.py
wclr/_compositing.py
wclr/_contrast.py
wclr/_math.py
wclr/_typing.py
wclr/_version.py
wclr/py.typed
wclr/_color/__init__.py
wclr/_color/core.py
wclr/_color/string.py
wclr/_color/utils.py
wclr-0.1.0.dist-info/LICENSE.txt
wclr-0.1.0.dist-info/METADATA
wclr-0.1.0.dist-info/WHEEL
wclr-0.1.0.dist-info/top_level.txt
wclr-0.1.0.dist-info/RECORD
