Metadata-Version: 2.1
Name: wclr
Version: 0.1.0
Summary: Web color tools
Home-page: https://gitlab.com/naubuan/wclr/
Author: naubuan
License: Apache License 2.0
Project-URL: Documentation, https://naubuan.gitlab.io/wclr/
Classifier: License :: OSI Approved :: Apache Software License
Classifier: Programming Language :: Python :: 3.8
Classifier: Programming Language :: Python :: 3.9
Classifier: Programming Language :: Python :: 3.10
Classifier: Programming Language :: Python :: 3.11
Requires-Python: >=3.8
License-File: LICENSE.txt
